nlpia2/__init__.py
nlpia2/alttext.py
nlpia2/charlist.py
nlpia2/chatgpt.py
nlpia2/config.py
nlpia2/constants.py
nlpia2/constants_stopwords.py
nlpia2/constants_uri_schemes.py
nlpia2/cuda_utils.py
nlpia2/futil.py
nlpia2/gec.py
nlpia2/google_drive.py
nlpia2/graph_plots.py
nlpia2/heatmaps.py
nlpia2/image_log_alttext_blip2_captions.txt
nlpia2/init.py
nlpia2/language_models.py
nlpia2/llm_benchmark.py
nlpia2/llm_survey.py
nlpia2/manuscript.py
nlpia2/nell.py
nlpia2/nessvec.py
nlpia2/netutils.py
nlpia2/paperswithcode.py
nlpia2/plots.py
nlpia2/py.typed
nlpia2/pycozo.py
nlpia2/pycozo_wrapper.py
nlpia2/spacy_language_model.py
nlpia2/spacy_pipes.py
nlpia2/string_encoding.py
nlpia2/string_normalizers.py
nlpia2/torch_gpu_benchmark.ipy.md
nlpia2/torch_utils.py
nlpia2/tutil.py
nlpia2/txtai_nli_mpnet.py
nlpia2/update_nlpia2_data.py
nlpia2/util.py
nlpia2/web.py
nlpia2/windows.py
nlpia2/bonus/__init__.py
nlpia2/bonus/manim.yml
nlpia2/bonus/manim_graph.py
nlpia2/bonus/playground.aisoma.de 7-word summary of _This is Just to Say_ poem by William Carlos Williams.png
nlpia2/bonus/ipython-sessions/char_trigram_index_and_language_model.ipy
nlpia2/bonus/ipython-sessions/char_trigram_language_model.py
nlpia2/bonus/ipython-sessions/quotes_language_model_first_order_markhov_chain.ipy
nlpia2/bonus/ipython-sessions/quotes_language_model_first_order_markhov_chain.py
nlpia2/ch01/NLU_NLG_graphviz.py
nlpia2/ch01/__init__.py
nlpia2/ch01/ch01.ipynb
nlpia2/ch01/ch01_ethnologue.py
nlpia2/ch01/ch01_re_tokenizers.hist.md
nlpia2/ch01/ch01_re_tokenizers.hist.py
nlpia2/ch01/text-NLU-vector-graphviz.gv
nlpia2/ch01/text-NLU-vector-graphviz.png
nlpia2/ch01/vector-NLG-text-graphviz.gv
nlpia2/ch02/README.md
nlpia2/ch02/__init__.py
nlpia2/ch02/book_thief_sentence_split_graphviz.py
nlpia2/ch02/bug-report-reader-dominick-bug-one-hot-encoding-NLP-2-ch2.ipynb
nlpia2/ch02/ch02.py
nlpia2/ch02/clean_fake_news.py
nlpia2/ch02/fake_news_big_data_techniques.ipy
nlpia2/ch02/fake_news_clean.py
nlpia2-0.2.0.dist-info/METADATA
nlpia2-0.2.0.dist-info/WHEEL
nlpia2-0.2.0.dist-info/licenses/AUTHORS.md
nlpia2-0.2.0.dist-info/licenses/LICENSE.md
nlpia2-0.2.0.dist-info/licenses/LICENSE.txt
nlpia2-0.2.0.dist-info/RECORD
