Metadata-Version: 2.4
Name: nlpia2
Version: 0.2.0
Summary: NLP utilities and examples for _Natural Language Processing in Action, 2nd Ed_, by Hobson Lane and Maria Dyshel
Author: Geoffrey Marshal, Sylvia Lee, Winnie Yeung @dcvionwinnie, Alex Rosengarten @alxrsngrtn, Jose Robins @jorobins
Author-email: Hobson Lane <gitlab@totalgood.com>, Maria Dyshel <maria@tangibleai.com>, Ethan Cavill <ethancavill@gmail.com>, Greg Thompson <greg@tangibleai.com>, Leo Hepis <leo@leohepis.com>, Mohammed Dala Ali <mms.dala@gmail.com>
License-File: AUTHORS.md
License-File: LICENSE.md
License-File: LICENSE.txt
Keywords: Deep Learning,LLM,Machine Learning,NLP,Natural Language Processing,RAG,Text Mining,Text Processing,Virtual Assistant,chatbot,command line,numpy,personal assistant,search,semantic search,text generation,vector-search
Classifier: Development Status :: 5 - Production/Stable
Classifier: Intended Audience :: Developers
Classifier: Intended Audience :: Education
Classifier: License :: OSI Approved :: GNU General Public License v3 or later (GPLv3+)
Classifier: Operating System :: OS Independent
Classifier: Programming Language :: Python :: 3
Classifier: Topic :: Communications
Classifier: Topic :: Communications :: Chat
Classifier: Topic :: Software Development :: Libraries :: Python Modules
Classifier: Topic :: Text Processing
Classifier: Topic :: Text Processing :: Linguistic
Requires-Python: >=3.11
Requires-Dist: beautifulsoup4>=4.12
Requires-Dist: bidict>=0.22.1
Requires-Dist: boto3>=1.34.6
Requires-Dist: configargparse>=1.7
Requires-Dist: cython>=3.0
Requires-Dist: dateparser>=1.1.8
Requires-Dist: edit-distance>=1.0.6
Requires-Dist: einops>=0.6.1
Requires-Dist: fastapi>=0.105.0
Requires-Dist: fuzzywuzzy
Requires-Dist: gradio
Requires-Dist: h5py>=3.9.0
Requires-Dist: html2text>=2020.1.16
Requires-Dist: huggingface-hub>=0.16.4
Requires-Dist: ipython
Requires-Dist: joblib<1.4,>=1.3.2
Requires-Dist: jsonlines>=3.1.0
Requires-Dist: jupyter
Requires-Dist: jupyter-console
Requires-Dist: jupyter-console>=6.6.3
Requires-Dist: jupyterlab>=4.0.10
Requires-Dist: langchain>=0.0.265
Requires-Dist: lxml>=4.9.3
Requires-Dist: matplotlib
Requires-Dist: matplotlib-inline
Requires-Dist: meilisearch
Requires-Dist: mistune>=3.0.1
Requires-Dist: nessvec>=0.2.0
Requires-Dist: nlpia2-wikipedia>=1.5.14
Requires-Dist: nltk>=3.8.1
Requires-Dist: numpy<1.27,>=1.26.2
Requires-Dist: openai>=0.27.8
Requires-Dist: pandas<2.3,>=2.2.0
Requires-Dist: pip
Requires-Dist: plotly
Requires-Dist: poetry
Requires-Dist: pronouncing>=0.2.0
Requires-Dist: psutil>=5.9.5
Requires-Dist: pytest-coverage
Requires-Dist: python-dotenv>=1.0.0
Requires-Dist: pyvis>=0.3.2
Requires-Dist: scikit-learn
Requires-Dist: seaborn>=0.13.0
Requires-Dist: sentence-transformers>=2.2.2
Requires-Dist: spacy
Requires-Dist: sphinx>=7.1.2
Requires-Dist: streamlit>=1.25.0
Requires-Dist: textacy>=0.13.0
Requires-Dist: toml>=0.10.2
Requires-Dist: tox>=4.8.0
Requires-Dist: tqdm>=4.66.1
Requires-Dist: unidecode>=1.3.6
Requires-Dist: xmltodict>=0.13.0
